[{"id": 1959, "page": null, "title": null, "notes": null, "commentary": "Here's the secret to sadstuck: lay it on thick with the dramatic irony about how she's REALLY excited to do all this fun stuff when they finally meet, when she will be DEFINITELY ALIVE enough to do those things. Also make the kid cry. Come to think of it, since Jade clearly saw John opening this package and reading the letter in a cloud vision, I wonder what she thought he was crying about? Probably tears of happiness due to all the FUN they were both about to have! :D"}]